/*     */ package net.ccbluex.liquidbounce.utils.render;@Metadata(mv = {1, 1, 16}, bv = {1, 0, 3}, k = 1, d1 = {"\000p\n\002\030\002\n\002\020\000\n\002\b\002\n\002\030\002\n\002\b\002\n\002\020\031\n\002\b\003\n\002\030\002\n\002\b\003\n\002\020\025\n\000\n\002\030\002\n\002\b\003\n\002\020\t\n\000\n\002\030\002\n\002\b\003\n\002\020\b\n\002\b\004\n\002\020\007\n\002\b\005\n\002\020\016\n\002\b\b\n\002\020\006\n\002\b\023\n\002\020\013\n\002\b\002\n\002\020\f\n\002\b\017\bÆ\002\030\0002\0020\001B\007\b\002¢\006\002\020\002J\020\020\026\032\0020\0272\006\020\030\032\0020\025H\007J\016\020\031\032\0020\0272\006\020\032\032\0020\033J*\020\034\032\004\030\0010\0272\006\020\035\032\0020\0252\006\020\036\032\0020\0332\006\020\037\032\0020 2\006\020!\032\0020 H\007J\030\020\"\032\0020\0272\006\020\030\032\0020\0252\006\020#\032\0020 H\007J\030\020$\032\0020\0272\006\020%\032\0020&2\b\b\002\020#\032\0020\033J\026\020'\032\0020\0272\006\020(\032\0020\0272\006\020)\032\0020 J \020*\032\0020\0272\006\020(\032\0020\0272\006\020\032\032\0020\0332\006\020\036\032\0020\033H\007J*\020+\032\0020\0272\006\020,\032\0020\0272\006\020-\032\0020\0272\b\b\002\020.\032\0020/2\b\b\002\020\030\032\0020/J\036\0200\032\0020\0332\006\0201\032\0020 2\006\0202\032\0020 2\006\0203\032\0020 J\026\0204\032\0020\0332\006\0205\032\0020 2\006\0206\032\0020 J \0207\032\0020\0272\006\0208\032\0020 2\006\0209\032\0020 2\b\b\002\020#\032\0020\033J8\020:\032\0020\0272\006\020\032\032\0020\0332\b\b\002\020;\032\0020 2\b\b\002\020<\032\0020 2\b\b\002\020=\032\0020\0332\b\b\002\020>\032\0020\033H\007J4\020?\032\004\030\0010\0272\006\020.\032\0020\0332\006\020\032\032\0020\0332\b\020@\032\004\030\0010\0272\b\020A\032\004\030\0010\0272\006\020B\032\0020CJ\016\020D\032\0020C2\006\020E\032\0020FJ\036\020G\032\0020\0272\006\020,\032\0020\0272\006\020-\032\0020\0272\006\020H\032\0020 JJ\020I\032\0020\0272\006\020\032\032\0020\0332\b\b\002\020;\032\0020 2\b\b\002\020<\032\0020 2\b\b\002\020=\032\0020\0332\b\b\002\020>\032\0020\0332\b\b\002\0202\032\0020 2\b\b\002\0203\032\0020 J\020\020J\032\0020\0272\006\020\030\032\0020\025H\007J\b\020K\032\0020\027H\007J\020\020K\032\0020\0272\006\020#\032\0020 H\007J\020\020K\032\0020\0272\006\020#\032\0020\033H\007J\020\020K\032\0020\0272\006\020\030\032\0020\025H\007J\030\020K\032\0020\0272\006\020\030\032\0020\0252\006\020#\032\0020 H\007J\030\020K\032\0020\0272\006\020\030\032\0020\0252\006\020#\032\0020\033H\007J\016\020L\032\0020\0272\006\020#\032\0020\033J\016\020M\032\0020&2\006\020N\032\0020&J\030\020O\032\0020\0272\006\020(\032\0020\0272\006\020#\032\0020 H\007J\026\020O\032\0020\0272\006\020(\032\0020\0272\006\020#\032\0020\033J(\020P\032\0020\0272\006\020\035\032\0020\0252\006\020\036\032\0020\0332\006\020\037\032\0020 2\006\020!\032\0020 H\007J\024\020Q\032\004\030\0010&2\b\020R\032\004\030\0010&H\007J\020\020S\032\0020&2\006\020T\032\0020&H\007R\026\020\003\032\n \005*\004\030\0010\0040\004X\004¢\006\002\n\000R\021\020\006\032\0020\007¢\006\b\n\000\032\004\b\b\020\tR\021\020\n\032\0020\013¢\006\b\n\000\032\004\b\f\020\rR\020\020\016\032\0020\0178\006X\004¢\006\002\n\000R\021\020\020\032\0020\021¢\006\b\n\000\032\004\b\022\020\023R\016\020\024\032\0020\025X\004¢\006\002\n\000¨\006U"}, d2 = {"Lnet/ccbluex/liquidbounce/utils/render/ColorUtils;", "", "()V", "COLOR_PATTERN", "Ljava/util/regex/Pattern;", "kotlin.jvm.PlatformType", "allowedCharactersArray", "", "getAllowedCharactersArray", "()[C", "gl", "Lnet/ccbluex/liquidbounce/features/module/modules/render/GodLightSync;", "getGl", "()Lnet/ccbluex/liquidbounce/features/module/modules/render/GodLightSync;", "hexColors", "", "hud", "Lnet/ccbluex/liquidbounce/features/module/modules/render/HUD;", "getHud", "()Lnet/ccbluex/liquidbounce/features/module/modules/render/HUD;", "startTime", "", "ALLColor", "Ljava/awt/Color;", "offset", "GodLight", "index", "", "LiquidSlowly", "time", "count", "qd", "", "sq", "TwoRainbow", "alpha", "colorCode", "code", "", "darker", "color", "percentage", "fade", "fade3", "a", "b", "speed", "", "getColor", "hueoffset", "saturation", "brightness", "getHealthColor", "health", "maxHealth", "healthColor", "hp", "maxHP", "hslRainbow", "lowest", "bigest", "indexOffset", "timeSplit", "interpolateColorsBackAndForth", "start", "end", "trueColor", "", "isAllowedCharacter", "character", "", "mix", "factor", "novoRainbow", "originalrainbow", "rainbow", "rainbowWithAlpha", "randomMagicText", "text", "reAlpha", "slowlyRainbow", "stripColor", "input", "translateAlternateColorCodes", "textToTranslate", "XSJClient"})
/*     */ public final class ColorUtils {
/*     */   @NotNull
/*     */   private static final char[] allowedCharactersArray;
/*     */   private static final Pattern COLOR_PATTERN;
/*     */   @JvmField
/*     */   @NotNull
/*     */   public static final int[] hexColors;
/*     */   private static final long startTime;
/*     */   @NotNull
/*     */   private static final HUD hud;
/*     */   @NotNull
/*     */   private static final GodLightSync gl;
/*     */   public static final ColorUtils INSTANCE;
/*     */   
/*     */   @NotNull
/*     */   public final char[] getAllowedCharactersArray() {
/*  18 */     return allowedCharactersArray;
/*     */   }
/*     */   
/*     */   public final boolean isAllowedCharacter(char character) {
/*  22 */     return (character != '§' && character >= ' ' && character != '');
/*     */   }
/*     */   @Nullable
/*     */   public final Color interpolateColorsBackAndForth(int speed, int index, @Nullable Color start, @Nullable Color end, boolean trueColor) {
/*  26 */     int angle = (int)((System.currentTimeMillis() / speed + index) % 360L);
/*  27 */     angle = ((angle >= 180) ? (360 - angle) : angle) * 2;
/*  28 */     return trueColor ? RenderUtils.interpolateColorHue(
/*  29 */         start, 
/*  30 */         end, 
/*  31 */         angle / 360.0F) : 
/*  32 */       RenderUtils.interpolateColorC(
/*  33 */         start, 
/*  34 */         end, 
/*  35 */         angle / 360.0F);
/*     */   }
/*     */   @JvmStatic
/*     */   @NotNull
/*     */   public static final Color slowlyRainbow(long time, int count, float qd, float sq) {
/*  40 */     Color color = new Color(Color.HSBtoRGB(((float)time + count * -3000000.0F) / 2 / 1.0E9F, qd, sq));
/*  41 */     return new Color(color.getRed() / 255.0F * true, color.getGreen() / 255.0F * true, color.getBlue() / 255.0F * true, color.getAlpha() / 255.0F);
/*     */   } @NotNull
/*     */   public final Color darker(@NotNull Color color, float percentage) {
/*  44 */     Intrinsics.checkParameterIsNotNull(color, "color"); return new Color((int)(color.getRed() * percentage), (int)(color.getGreen() * percentage), (int)(color.getBlue() * percentage), (int)(color.getAlpha() * percentage));
/*     */   } @NotNull
/*     */   public final Color colorCode(@NotNull String code, int alpha) {
/*  47 */     Intrinsics.checkParameterIsNotNull(code, "code"); String str = code; boolean bool = false; Intrinsics.checkExpressionValueIsNotNull(str.toLowerCase(), "(this as java.lang.String).toLowerCase()"); str = str.toLowerCase(); switch (str.hashCode())
/*     */     
/*     */     { 
/*     */ 
/*     */ 
/*     */ 
/*     */ 
/*     */ 
/*     */ 
/*     */ 
/*     */ 
/*     */ 
/*     */ 
/*     */ 
/*     */ 
/*     */ 
/*     */ 
/*     */ 
/*     */ 
/*     */ 
/*     */ 
/*     */ 
/*     */ 
/*     */ 
/*     */ 
/*     */ 
/*     */ 
/*     */ 
/*     */ 
/*     */       
/*     */       case 97:
/*  78 */         if (str.equals("a"))
/*  79 */           return new Color(85, 255, 85, alpha);  break;
/*     */       case 98:
/*  81 */         if (str.equals("b"))
/*  82 */           return new Color(85, 255, 255, alpha);  break;
/*     */       case 99:
/*  84 */         if (str.equals("c"))
/*  85 */           return new Color(255, 85, 85, alpha);  break;
/*     */       case 100:
/*  87 */         if (str.equals("d"))
/*  88 */           return new Color(255, 85, 255, alpha);  break;
/*     */       case 101:
/*  90 */         if (str.equals("e"))
/*  91 */           return new Color(255, 255, 85, alpha);  break;case 48: if (str.equals("0")) return new Color(0, 0, 0, alpha);  break;case 49: if (str.equals("1")) return new Color(0, 0, 170, alpha);  break;case 50: if (str.equals("2")) return new Color(0, 170, 0, alpha);  break;case 51: if (str.equals("3")) return new Color(0, 170, 170, alpha);  break;case 52: if (str.equals("4")) return new Color(170, 0, 0, alpha);  break;case 53: if (str.equals("5")) return new Color(170, 0, 170, alpha);  break;case 54: if (str.equals("6")) return new Color(255, 170, 0, alpha);  break;case 55: if (str.equals("7"))
/*     */           return new Color(170, 170, 170, alpha);  break;case 56: if (str.equals("8"))
/*     */           return new Color(85, 85, 85, alpha);  break;case 57: if (str.equals("9"))
/*  94 */           return new Color(85, 85, 255, alpha);  break; }  return new Color(255, 255, 255, alpha);
/*     */   }
/*     */ 
/*     */ 
/*     */ 
/*     */ 
/*     */ 
/*     */ 
/*     */ 
/*     */ 
/*     */ 
/*     */ 
/*     */ 
/*     */ 
/*     */ 
/*     */ 
/*     */ 
/*     */ 
/*     */ 
/*     */ 
/*     */ 
/*     */   
/*     */   @NotNull
/*     */   public final Color mix(@NotNull Color a, @NotNull Color b, float factor) {
/* 118 */     Intrinsics.checkParameterIsNotNull(a, "a"); Intrinsics.checkParameterIsNotNull(b, "b"); float f = factor; boolean bool1 = (f >= 0.0F && f <= 1.0F) ? true : false, bool2 = false, bool3 = false; if (!bool1) { int $i$a$-require-ColorUtils$mix$1 = 0; String str = "Color factor should be between 0 and 1"; throw (Throwable)new IllegalArgumentException(str.toString()); }
/*     */     
/* 120 */     return new Color(
/* 121 */         (int)(a.getRed() * factor + b.getRed() * (true - factor)), 
/* 122 */         (int)(a.getGreen() * factor + b.getGreen() * (true - factor)), 
/* 123 */         (int)(a.getBlue() * factor + b.getBlue() * (true - factor)));
/*     */   }
/*     */ 
/*     */   
/*     */   @NotNull
/*     */   public final Color fade3(@NotNull Color a, @NotNull Color b, double speed, double offset) {
/* 129 */     Intrinsics.checkParameterIsNotNull(a, "a"); Intrinsics.checkParameterIsNotNull(b, "b"); double time = System.currentTimeMillis() * speed + offset;
/* 130 */     boolean bool = false; double factor = Math.abs(Math.sin(time));
/*     */     
/* 132 */     return mix(a, b, (float)factor);
/*     */   }
/*     */   
/*     */   public final int getColor(float hueoffset, float saturation, float brightness) {
/* 136 */     float speed = 4500.0F;
/* 137 */     float hue = (float)(System.currentTimeMillis() % (int)speed) / speed;
/* 138 */     return Color.HSBtoRGB(hue - hueoffset / 54, saturation, brightness);
/*     */   }
/*     */ 
/*     */ 
/*     */ 
/*     */   
/*     */   @JvmStatic
/*     */   @Nullable
/*     */   public static final String stripColor(@Nullable String input) {
/*     */     // Byte code:
/*     */     //   0: getstatic net/ccbluex/liquidbounce/utils/render/ColorUtils.COLOR_PATTERN : Ljava/util/regex/Pattern;
/*     */     //   3: aload_0
/*     */     //   4: dup
/*     */     //   5: ifnull -> 14
/*     */     //   8: checkcast java/lang/CharSequence
/*     */     //   11: goto -> 17
/*     */     //   14: pop
/*     */     //   15: aconst_null
/*     */     //   16: areturn
/*     */     //   17: invokevirtual matcher : (Ljava/lang/CharSequence;)Ljava/util/regex/Matcher;
/*     */     //   20: ldc_w ''
/*     */     //   23: invokevirtual replaceAll : (Ljava/lang/String;)Ljava/lang/String;
/*     */     //   26: areturn
/*     */     // Line number table:
/*     */     //   Java source line number -> byte code offset
/*     */     //   #143	-> 0
/*     */     //   #143	-> 14
/*     */     // Local variable table:
/*     */     //   start	length	slot	name	descriptor
/*     */     //   0	27	0	input	Ljava/lang/String;
/*     */   }
/*     */ 
/*     */ 
/*     */ 
/*     */   
/*     */   @JvmStatic
/*     */   @NotNull
/*     */   public static final Color hslRainbow(int index, float lowest, float bigest, int indexOffset, int timeSplit) {
/* 156 */     Intrinsics.checkExpressionValueIsNotNull(Color.getHSBColor(
/* 157 */           Math.abs(((int)(System.currentTimeMillis() - startTime) + index * indexOffset) / timeSplit % 2 - true) * (bigest - lowest) + lowest, 
/* 158 */           0.7F, 
/* 159 */           1.0F), "Color.getHSBColor(\n     …\n            1f\n        )"); return Color.getHSBColor(Math.abs(((int)(System.currentTimeMillis() - startTime) + index * indexOffset) / timeSplit % 2 - true) * (bigest - lowest) + lowest, 0.7F, 1.0F);
/*     */   }
/*     */   
/*     */   @JvmStatic
/*     */   @NotNull
/*     */   public static final Color fade(@NotNull Color color, int index, int count) {
/* 165 */     Intrinsics.checkParameterIsNotNull(color, "color"); float[] hsb = new float[3];
/* 166 */     Color.RGBtoHSB(color.getRed(), color.getGreen(), color.getBlue(), hsb);
/* 167 */     float brightness = 
/* 168 */       Math.abs(((float)(System.currentTimeMillis() % 2000L) / 1000.0F + index / count * 2.0F) % 2.0F - 1.0F);
/* 169 */     brightness = 0.5F + 0.5F * brightness;
/* 170 */     hsb[2] = brightness % 2.0F;
/* 171 */     return new Color(Color.HSBtoRGB(hsb[0], hsb[1], hsb[2]));
/*     */   }
/*     */   @JvmStatic
/*     */   @NotNull
/*     */   public static final String translateAlternateColorCodes(@NotNull String textToTranslate) {
/* 176 */     Intrinsics.checkParameterIsNotNull(textToTranslate, "textToTranslate"); String str = textToTranslate; int j = 0; Intrinsics.checkExpressionValueIsNotNull(str.toCharArray(), "(this as java.lang.String).toCharArray()"); char[] chars = str.toCharArray();
/*     */     
/* 178 */     for (byte b = 0; b < j; b++) {
/* 179 */       if (chars[b] == '&' && StringsKt.contains("0123456789AaBbCcDdEeFfKkLlMmNnOoRr", chars[b + 1], true)) {
/* 180 */         chars[b] = '§';
/* 181 */         chars[b + 1] = Character.toLowerCase(chars[b + 1]);
/*     */       } 
/*     */     } 
/*     */     
/* 185 */     int i = 0; return new String(chars);
/*     */   }
/*     */   @NotNull
/*     */   public final String randomMagicText(@NotNull String text) {
/* 189 */     Intrinsics.checkParameterIsNotNull(text, "text"); StringBuilder stringBuilder = new StringBuilder();
/* 190 */     String allowedCharacters = 
/* 191 */       "ÀÁÂÈÊËÍÓÔÕÚßãõğİıŒœŞşŴŵžȇ\000\000\000\000\000\000\000 !\"#$%&'()*+,-./0123456789:;<=>?@ABCDEFGHIJKLMNOPQRSTUVWXYZ[\\]^_`abcdefghijklmnopqrstuvwxyz{|}~\000ÇüéâäàåçêëèïîìÄÅÉæÆôöòûùÿÖÜø£Ø×ƒáíóúñÑªº¿®¬½¼¡«»░▒▓│┤╡╢╖╕╣║╗╝╜╛┐└┴┬├─┼╞╟╚╔╩╦╠═╬╧╨╤╥╙╘╒╓╫╪┘┌█▄▌▐▀αβΓπΣσμτΦΘΩδ∞∅∈∩≡±≥≤⌠⌡÷≈°∙·√ⁿ²■\000";
/*     */     
/* 193 */     String str1 = text; boolean bool = false; Intrinsics.checkExpressionValueIsNotNull(str1.toCharArray(), "(this as java.lang.String).toCharArray()"); for (char c : str1.toCharArray()) {
/* 194 */       if (isAllowedCharacter(c)) {
/* 195 */         int index = (new Random()).nextInt(allowedCharacters.length());
/* 196 */         String str = allowedCharacters; StringBuilder stringBuilder1 = stringBuilder; boolean bool1 = false; Intrinsics.checkExpressionValueIsNotNull(str.toCharArray(), "(this as java.lang.String).toCharArray()"); char[] arrayOfChar = str.toCharArray(); stringBuilder1.append(arrayOfChar[index]);
/*     */       } 
/*     */     } 
/*     */     
/* 200 */     Intrinsics.checkExpressionValueIsNotNull(stringBuilder.toString(), "stringBuilder.toString()"); return stringBuilder.toString();
/*     */   }
/*     */   @JvmStatic
/*     */   @NotNull
/*     */   public static final Color rainbow() {
/* 205 */     Color currentColor = new Color(Color.HSBtoRGB((float)(System.nanoTime() + 400000L) / 1.0E10F % true, 1.0F, 1.0F));
/* 206 */     return new Color(
/* 207 */         currentColor.getRed() / 255.0F * 1.0F, 
/* 208 */         currentColor.getGreen() / 255.0F * 1.0F, 
/* 209 */         currentColor.getBlue() / 255.0F * 1.0F, 
/* 210 */         currentColor.getAlpha() / 255.0F);
/*     */   }
/*     */ 
/*     */ 
/*     */   
/*     */   @JvmStatic
/*     */   @NotNull
/*     */   public static final Color rainbow(long offset) {
/* 218 */     Color currentColor = new Color(Color.HSBtoRGB((float)(System.nanoTime() + offset) / 1.0E10F % true, 1.0F, 1.0F));
/* 219 */     return new Color(
/* 220 */         currentColor.getRed() / 255.0F * 1.0F, currentColor.getGreen() / 255.0F * 1.0F, currentColor.getBlue() / 255.0F * 1.0F, 
/* 221 */         currentColor.getAlpha() / 255.0F);
/*     */   }
/*     */   
/*     */   @JvmStatic
/*     */   @NotNull
/* 226 */   public static final Color rainbow(float alpha) { return rainbow(400000L, alpha); }
/*     */   @JvmStatic
/*     */   @NotNull
/* 229 */   public static final Color rainbow(int alpha) { return rainbow(400000L, alpha / 255); } @JvmStatic
/*     */   @NotNull
/*     */   public static final Color rainbow(long offset, int alpha) {
/* 232 */     return rainbow(offset, alpha / 'ÿ');
/*     */   } @JvmStatic
/*     */   @NotNull
/*     */   public static final Color ALLColor(long offset) {
/* 236 */     Color currentColor = new Color(
/* 237 */         Color.HSBtoRGB(
/* 238 */           (float)((Minecraft.func_71410_x()).field_71439_g.field_70173_aa / 50.0D + Math.sin(1.6D) % true), 
/* 239 */           0.4F, 
/* 240 */           0.9F));
/*     */ 
/*     */ 
/*     */     
/* 244 */     return new Color(currentColor.getRGB());
/*     */   }
/*     */   @JvmStatic
/*     */   @NotNull
/*     */   public static final Color originalrainbow(long offset) {
/* 249 */     Color currentColor = new Color(Color.HSBtoRGB((float)(System.nanoTime() + offset) / 1.0E10F % true, 1.0F, 1.0F));
/* 250 */     return new Color(
/* 251 */         currentColor.getRed() / 255.0F * 1.0F, currentColor.getGreen() / 255.0F * 1.0F, currentColor.getBlue() / 255.0F * 1.0F, 
/* 252 */         currentColor.getAlpha() / 255.0F);
/*     */   }
/*     */   @NotNull
/* 255 */   public final HUD getHud() { return hud; } @NotNull
/*     */   public final GodLightSync getGl() {
/* 257 */     return gl;
/*     */   }
/*     */ 
/*     */ 
/*     */ 
/*     */ 
/*     */ 
/*     */ 
/*     */   
/*     */   @NotNull
/*     */   public final Color novoRainbow(int index, float lowest, float bigest, int indexOffset, int timeSplit, float saturation, float brightness) {
/* 268 */     Intrinsics.checkExpressionValueIsNotNull(Color.getHSBColor(Math.abs(((int)(System.currentTimeMillis() - startTime) + index * indexOffset) / timeSplit % 2 - true) * (bigest - lowest) + lowest, saturation, brightness), "Color.getHSBColor((abs((…, saturation, brightness)"); return Color.getHSBColor(Math.abs(((int)(System.currentTimeMillis() - startTime) + index * indexOffset) / timeSplit % 2 - true) * (bigest - lowest) + lowest, saturation, brightness);
/*     */   }
/*     */   
/*     */   @NotNull
/*     */   public final Color GodLight(int index) {
/* 273 */     Intrinsics.checkExpressionValueIsNotNull(VisualUtils.getGradientOffset(new Color(((Number)gl.getR().get()).intValue(), ((Number)gl.getG().get()).intValue(), ((Number)gl.getB().get()).intValue(), 1), new Color(((Number)gl.getR2().get()).intValue(), ((Number)gl.getG2().get()).intValue(), ((Number)gl.getB2().get()).intValue(), 1), Math.abs((
/* 274 */             System.currentTimeMillis() / 10140L) + index / 1.5D) / 
/* 275 */           10), "VisualUtils.getGradientO…       .toDouble()) /10))"); return VisualUtils.getGradientOffset(new Color(((Number)gl.getR().get()).intValue(), ((Number)gl.getG().get()).intValue(), ((Number)gl.getB().get()).intValue(), 1), new Color(((Number)gl.getR2().get()).intValue(), ((Number)gl.getG2().get()).intValue(), ((Number)gl.getB2().get()).intValue(), 1), Math.abs((System.currentTimeMillis() / 10140L) + index / 1.5D) / 10);
/*     */   } @JvmStatic
/*     */   @Nullable
/*     */   public static final Color LiquidSlowly(long time, int count, float qd, float sq) {
/* 279 */     Color color = new Color(Color.HSBtoRGB(((float)time + count * -3000000.0F) / 2 / 1.0E9F, qd, sq));
/* 280 */     return new Color(color.getRed() / 255.0F * true, color.getGreen() / 255.0F * true, color.getBlue() / 255.0F * true, color.getAlpha() / 255.0F);
/*     */   }
/*     */   @JvmStatic
/*     */   @NotNull
/*     */   public static final Color rainbow(long offset, float alpha) {
/* 285 */     Color currentColor = new Color(Color.HSBtoRGB((float)(System.nanoTime() + offset) / 1.0E10F % true, 1.0F, 1.0F));
/* 286 */     return new Color(currentColor.getRed() / 255.0F * 1.0F, currentColor.getGreen() / 255.0F * 1.0F, currentColor.getBlue() / 255.0F * 1.0F, alpha);
/*     */   }
/*     */   @JvmStatic
/*     */   @NotNull
/*     */   public static final Color TwoRainbow(long offset, float alpha) {
/* 291 */     Color currentColor = new Color(Color.HSBtoRGB((float)(System.nanoTime() + offset) / 9.0E10F % true, 0.75F, 0.8F));
/* 292 */     return new Color(
/* 293 */         currentColor.getRed() / 255.0F * 1.0F, 
/* 294 */         currentColor.getGreen() / 255.0F * 1.0F, 
/* 295 */         currentColor.getBlue() / 255.0F * 1.0F, 
/* 296 */         alpha);
/*     */   }
/*     */   
/*     */   @NotNull
/*     */   public final Color healthColor(float hp, float maxHP, int alpha) {
/* 301 */     int pct = (int)(hp / maxHP * 255.0F);
/* 302 */     int i = 255 - pct; char c = 'ÿ'; boolean bool1 = false; int j = Math.min(i, c); c = Character.MIN_VALUE; bool1 = false; j = Math.max(i, c); i = 255; j = j; c = Character.MIN_VALUE; int k = Math.min(pct, i); c = Character.MIN_VALUE; j = j; bool1 = false; k = Math.max(i, c); int m = alpha; boolean bool2 = false; int n = k, i1 = j; return new Color(i1, n, bool2, m);
/*     */   }
/*     */   
/*     */   public final int getHealthColor(float health, float maxHealth) {
/* 306 */     float f1 = health;
/* 307 */     if (f1 > 20) {
/* 308 */       f1 = 20.0F;
/*     */     }
/* 310 */     float[] fractions = { 0.0F, 0.5F, 1.0F };
/* 311 */     Color[] colors = { Color.RED, Color.YELLOW, Color.GREEN };
/* 312 */     float progress = f1 * 5 * 0.01F;
/* 313 */     if (Colors.blendColors(fractions, colors, progress) == null) Intrinsics.throwNpe();  Color customColor = Colors.blendColors(fractions, colors, progress).brighter();
/* 314 */     Intrinsics.checkExpressionValueIsNotNull(customColor, "customColor"); return customColor.getRGB();
/*     */   } @JvmStatic
/*     */   @NotNull
/*     */   public static final Color reAlpha(@NotNull Color color, float alpha) {
/* 318 */     Intrinsics.checkParameterIsNotNull(color, "color"); return new Color(color.getRed() / 255.0F, color.getGreen() / 255.0F, color.getBlue() / 255.0F, RangesKt.coerceIn(alpha, 0.0F, 1.0F));
/*     */   } @NotNull
/*     */   public final Color reAlpha(@NotNull Color color, int alpha) {
/* 321 */     Intrinsics.checkParameterIsNotNull(color, "color"); return new Color(color.getRed(), color.getGreen(), color.getBlue(), alpha);
/*     */   }
/*     */   @NotNull
/*     */   public final Color rainbowWithAlpha(int alpha) {
/* 325 */     return reAlpha(hslRainbow$default(1, 0.0F, 0.0F, 0, 0, 30, null), alpha);
/*     */   }
/*     */   
/*     */   static {
/*     */     // Byte code:
/*     */     //   0: new net/ccbluex/liquidbounce/utils/render/ColorUtils
/*     */     //   3: dup
/*     */     //   4: invokespecial <init> : ()V
/*     */     //   7: astore_0
/*     */     //   8: aload_0
/*     */     //   9: putstatic net/ccbluex/liquidbounce/utils/render/ColorUtils.INSTANCE : Lnet/ccbluex/liquidbounce/utils/render/ColorUtils;
/*     */     //   12: bipush #15
/*     */     //   14: newarray char
/*     */     //   16: dup
/*     */     //   17: iconst_0
/*     */     //   18: bipush #47
/*     */     //   20: castore
/*     */     //   21: dup
/*     */     //   22: iconst_1
/*     */     //   23: bipush #10
/*     */     //   25: castore
/*     */     //   26: dup
/*     */     //   27: iconst_2
/*     */     //   28: bipush #13
/*     */     //   30: castore
/*     */     //   31: dup
/*     */     //   32: iconst_3
/*     */     //   33: bipush #9
/*     */     //   35: castore
/*     */     //   36: dup
/*     */     //   37: iconst_4
/*     */     //   38: iconst_0
/*     */     //   39: castore
/*     */     //   40: dup
/*     */     //   41: iconst_5
/*     */     //   42: bipush #12
/*     */     //   44: castore
/*     */     //   45: dup
/*     */     //   46: bipush #6
/*     */     //   48: bipush #96
/*     */     //   50: castore
/*     */     //   51: dup
/*     */     //   52: bipush #7
/*     */     //   54: bipush #63
/*     */     //   56: castore
/*     */     //   57: dup
/*     */     //   58: bipush #8
/*     */     //   60: bipush #42
/*     */     //   62: castore
/*     */     //   63: dup
/*     */     //   64: bipush #9
/*     */     //   66: bipush #92
/*     */     //   68: castore
/*     */     //   69: dup
/*     */     //   70: bipush #10
/*     */     //   72: bipush #60
/*     */     //   74: castore
/*     */     //   75: dup
/*     */     //   76: bipush #11
/*     */     //   78: bipush #62
/*     */     //   80: castore
/*     */     //   81: dup
/*     */     //   82: bipush #12
/*     */     //   84: bipush #124
/*     */     //   86: castore
/*     */     //   87: dup
/*     */     //   88: bipush #13
/*     */     //   90: bipush #34
/*     */     //   92: castore
/*     */     //   93: dup
/*     */     //   94: bipush #14
/*     */     //   96: bipush #58
/*     */     //   98: castore
/*     */     //   99: putstatic net/ccbluex/liquidbounce/utils/render/ColorUtils.allowedCharactersArray : [C
/*     */     //   102: ldc_w '(?i)§[0-9A-FK-OR]'
/*     */     //   105: invokestatic compile : (Ljava/lang/String;)Ljava/util/regex/Pattern;
/*     */     //   108: putstatic net/ccbluex/liquidbounce/utils/render/ColorUtils.COLOR_PATTERN : Ljava/util/regex/Pattern;
/*     */     //   111: bipush #16
/*     */     //   113: newarray int
/*     */     //   115: putstatic net/ccbluex/liquidbounce/utils/render/ColorUtils.hexColors : [I
/*     */     //   118: bipush #16
/*     */     //   120: istore_1
/*     */     //   121: iconst_0
/*     */     //   122: istore_2
/*     */     //   123: iconst_0
/*     */     //   124: istore_3
/*     */     //   125: iconst_0
/*     */     //   126: istore_3
/*     */     //   127: iload_1
/*     */     //   128: istore #4
/*     */     //   130: iload_3
/*     */     //   131: iload #4
/*     */     //   133: if_icmpge -> 250
/*     */     //   136: iload_3
/*     */     //   137: istore #5
/*     */     //   139: iconst_0
/*     */     //   140: istore #6
/*     */     //   142: iload #5
/*     */     //   144: iconst_3
/*     */     //   145: ishr
/*     */     //   146: iconst_1
/*     */     //   147: iand
/*     */     //   148: bipush #85
/*     */     //   150: imul
/*     */     //   151: istore #7
/*     */     //   153: iload #5
/*     */     //   155: iconst_2
/*     */     //   156: ishr
/*     */     //   157: iconst_1
/*     */     //   158: iand
/*     */     //   159: sipush #170
/*     */     //   162: imul
/*     */     //   163: iload #7
/*     */     //   165: iadd
/*     */     //   166: iload #5
/*     */     //   168: bipush #6
/*     */     //   170: if_icmpne -> 178
/*     */     //   173: bipush #85
/*     */     //   175: goto -> 179
/*     */     //   178: iconst_0
/*     */     //   179: iadd
/*     */     //   180: istore #8
/*     */     //   182: iload #5
/*     */     //   184: iconst_1
/*     */     //   185: ishr
/*     */     //   186: iconst_1
/*     */     //   187: iand
/*     */     //   188: sipush #170
/*     */     //   191: imul
/*     */     //   192: iload #7
/*     */     //   194: iadd
/*     */     //   195: istore #9
/*     */     //   197: iload #5
/*     */     //   199: iconst_1
/*     */     //   200: iand
/*     */     //   201: sipush #170
/*     */     //   204: imul
/*     */     //   205: iload #7
/*     */     //   207: iadd
/*     */     //   208: istore #10
/*     */     //   210: getstatic net/ccbluex/liquidbounce/utils/render/ColorUtils.hexColors : [I
/*     */     //   213: iload #5
/*     */     //   215: iload #8
/*     */     //   217: sipush #255
/*     */     //   220: iand
/*     */     //   221: bipush #16
/*     */     //   223: ishl
/*     */     //   224: iload #9
/*     */     //   226: sipush #255
/*     */     //   229: iand
/*     */     //   230: bipush #8
/*     */     //   232: ishl
/*     */     //   233: ior
/*     */     //   234: iload #10
/*     */     //   236: sipush #255
/*     */     //   239: iand
/*     */     //   240: ior
/*     */     //   241: iastore
/*     */     //   242: nop
/*     */     //   243: nop
/*     */     //   244: iinc #3, 1
/*     */     //   247: goto -> 130
/*     */     //   250: nop
/*     */     //   251: invokestatic currentTimeMillis : ()J
/*     */     //   254: putstatic net/ccbluex/liquidbounce/utils/render/ColorUtils.startTime : J
/*     */     //   257: getstatic net/ccbluex/liquidbounce/Retreat.INSTANCE : Lnet/ccbluex/liquidbounce/Retreat;
/*     */     //   260: invokevirtual getModuleManager : ()Lnet/ccbluex/liquidbounce/features/module/ModuleManager;
/*     */     //   263: ldc_w net/ccbluex/liquidbounce/features/module/modules/render/HUD
/*     */     //   266: invokevirtual getModule : (Ljava/lang/Class;)Lnet/ccbluex/liquidbounce/features/module/Module;
/*     */     //   269: dup
/*     */     //   270: ifnonnull -> 284
/*     */     //   273: new kotlin/TypeCastException
/*     */     //   276: dup
/*     */     //   277: ldc_w 'null cannot be cast to non-null type net.ccbluex.liquidbounce.features.module.modules.render.HUD'
/*     */     //   280: invokespecial <init> : (Ljava/lang/String;)V
/*     */     //   283: athrow
/*     */     //   284: checkcast net/ccbluex/liquidbounce/features/module/modules/render/HUD
/*     */     //   287: putstatic net/ccbluex/liquidbounce/utils/render/ColorUtils.hud : Lnet/ccbluex/liquidbounce/features/module/modules/render/HUD;
/*     */     //   290: getstatic net/ccbluex/liquidbounce/Retreat.INSTANCE : Lnet/ccbluex/liquidbounce/Retreat;
/*     */     //   293: invokevirtual getModuleManager : ()Lnet/ccbluex/liquidbounce/features/module/ModuleManager;
/*     */     //   296: ldc_w net/ccbluex/liquidbounce/features/module/modules/render/GodLightSync
/*     */     //   299: invokevirtual getModule : (Ljava/lang/Class;)Lnet/ccbluex/liquidbounce/features/module/Module;
/*     */     //   302: dup
/*     */     //   303: ifnonnull -> 317
/*     */     //   306: new kotlin/TypeCastException
/*     */     //   309: dup
/*     */     //   310: ldc_w 'null cannot be cast to non-null type net.ccbluex.liquidbounce.features.module.modules.render.GodLightSync'
/*     */     //   313: invokespecial <init> : (Ljava/lang/String;)V
/*     */     //   316: athrow
/*     */     //   317: checkcast net/ccbluex/liquidbounce/features/module/modules/render/GodLightSync
/*     */     //   320: putstatic net/ccbluex/liquidbounce/utils/render/ColorUtils.gl : Lnet/ccbluex/liquidbounce/features/module/modules/render/GodLightSync;
/*     */     //   323: return
/*     */     // Line number table:
/*     */     //   Java source line number -> byte code offset
/*     */     //   #16	-> 0
/*     */     //   #19	-> 12
/*     */     //   #98	-> 102
/*     */     //   #103	-> 111
/*     */     //   #106	-> 118
/*     */     //   #107	-> 142
/*     */     //   #109	-> 153
/*     */     //   #110	-> 182
/*     */     //   #111	-> 197
/*     */     //   #113	-> 210
/*     */     //   #114	-> 242
/*     */     //   #106	-> 244
/*     */     //   #115	-> 250
/*     */     //   #146	-> 251
/*     */     //   #255	-> 257
/*     */     //   #257	-> 290
/*     */     // Local variable table:
/*     */     //   start	length	slot	name	descriptor
/*     */     //   210	32	10	blue	I
/*     */     //   197	45	9	green	I
/*     */     //   182	60	8	red	I
/*     */     //   153	89	7	baseColor	I
/*     */     //   139	104	5	i	I
/*     */     //   142	101	6	$i$a$-repeat-ColorUtils$1	I
/*     */   }
/*     */ }


/* Location:              C:\Users\Administrator\Desktop\XSJ Client v2.3 New Year's Special Edition.jar!\net\ccbluex\liquidbounc\\utils\render\ColorUtils.class
 * Java compiler version: 8 (52.0)
 * JD-Core Version:       1.1.3
 */